novasystem/__init__.py
novasystem/cli/__init__.py
novasystem/cli/main.py
novasystem/core/__init__.py
novasystem/core/app.py
novasystem/core/logic.py
novasystem/core/setup.py
novasystem/gui/__init__.py
novasystem/gui/main.py
novasystem/main.py
novasystem-0.1.0.dist-info/METADATA
novasystem-0.1.0.dist-info/WHEEL
novasystem-0.1.0.dist-info/entry_points.txt
novasystem-0.1.0.dist-info/RECORD
